{
  "nextgen": {
    "iv": "YJYX/r3Ecb7Luea2i6Hb8g==\n",
    "cipher": "aes-256-cbc",
    "version": 1,
    "encrypted_data": "oxKNvqqbesCxq9tK5X5ObYKBUeXvlXljhL1kiW+UpVWuBNXgVXsykNXccMyR\nM6QB\n"
  },
  "orchard": {
    "iv": "RdLuAH/e4ksPW0oWjr3z+Q==\n",
    "cipher": "aes-256-cbc",
    "version": 1,
    "encrypted_data": "NO8+v5xjU57EAj+J1IfYMMKVOT6WJFdy5TkB1r4KKjuqppLQcLgxTDSERWWI\nP4ow\n"
  },
  "believe": {
    "iv": "3m64+HKdQBpp3q7Mf8dujg==\n",
    "cipher": "aes-256-cbc",
    "version": 1,
    "encrypted_data": "sA00WA7l7eTJ7imybhx2x7767rYkMfvAmz05byaK8OZ7/UsfzTARoPOloUO6\nyaei\n"
  },
  "onerpm": {
    "iv": "FMoDnY5vYsTft0Yu2pBRaw==\n",
    "cipher": "aes-256-cbc",
    "version": 1,
    "encrypted_data": "e05hd2Nzd7pTIE2wMbbOHG4Gp/qRNpm+BPUwLo4AQ+f965a6XTnt3qM5NdtI\n4PuZ\n"
  },
  "PremiereNetworks": {
    "iv": "P0lGgaBpULNJqn9w6YEj9Q==\n",
    "cipher": "aes-256-cbc",
    "version": 1,
    "encrypted_data": "495NOt/n0ZKh2uwterRyM/FUh3NB8DiHIo4vpZHe21BxerPC+dRXPToR8nnE\nYzNj\n"
  },
  "E1": {
    "iv": "n7SeFry7vsq33BuZiJXy8w==\n",
    "cipher": "aes-256-cbc",
    "version": 1,
    "encrypted_data": "Vaxiiw2PgFbAxwngl5rAZxj/g5jmJkjuETt2SUqzIJ7tk5OvQwrrhlL+Ncqp\n0s0v\n"
  },
  "cdbaby": {
    "iv": "mfFEm8MAOh9n+Yif5GBd9w==\n",
    "cipher": "aes-256-cbc",
    "version": 1,
    "encrypted_data": "wjvuVgFNgrPNlVU7918eFQuN3jwSLO1aVd9V4kCCC28pjIpgqd4L8UP4Rjxf\nlreR\n"
  },
  "clearchannel": {
    "iv": "O0Yq+ffL9KQKg7mtBCjx7Q==\n",
    "cipher": "aes-256-cbc",
    "version": 1,
    "encrypted_data": "d4xvkUqoPdlSLgCojroucvLym5Ifg9j6rO5QPwu0+Q8YtjD3OBIKiIMa26lQ\nnY3s\n"
  },
  "directtv": {
    "iv": "EFk3K1910PlwVBGRppzsPQ==\n",
    "cipher": "aes-256-cbc",
    "version": 1,
    "encrypted_data": "ttjAv2/crbTO6cyKn4A+GNY7yoiXgKT8/Gnruoz8LJkSjmY90COWJCSJlqDB\nI6WY\n"
  },
  "Rebeat": {
    "iv": "ObKqQa1KAg+bDMJZPgrnPA==\n",
    "cipher": "aes-256-cbc",
    "version": 1,
    "encrypted_data": "erJasOFxGLEciZCLrZZXiFPMdELkb/53Y6bUfTiNyvFvqU1GLtf9GrAANF2F\nJiZu\n"
  },
  "EPM": {
    "iv": "hsKQNESpvYvkschTnXvwKw==\n",
    "cipher": "aes-256-cbc",
    "version": 1,
    "encrypted_data": "AXOS3NrneCKEweKebhK30ud0YWTRdUsrpIK/JY87D2qcKILS/6s23QWqzIHn\nADH8\n"
  },
  "fuga": {
    "iv": "3nk5uWFdL3KnSXkHnR36vQ==\n",
    "cipher": "aes-256-cbc",
    "version": 1,
    "encrypted_data": "VElc1hn+Tp6i1IYoknaqGwa9/AWskXZpULIFHL6n4jupXKQVlCQpq41S5JqX\nnu7w\n"
  },
  "Sleaze": {
    "iv": "Bi1T+k6u96sjBLghuRgo7w==\n",
    "cipher": "aes-256-cbc",
    "version": 1,
    "encrypted_data": "RLl+694x49A2h/npJRtcEjVZQWdAtIgcFFIertN/gDEnb72+Ag5oJkyZ1gJJ\ni+yQ\n"
  },
  "bleacherreport": {
    "iv": "XhpGEzNEDG/AdyDLioeNIw==\n",
    "cipher": "aes-256-cbc",
    "version": 1,
    "encrypted_data": "nBWj3IMx6Jy3QQiTW0DCsFQR1HsNFw0lP5SYZJ/9vfRX6BnohLFZVHHfzA70\nEL8u\n"
  },
  "collegehumor": {
    "iv": "H3xgyzNehI87kY59A8cXeQ==\n",
    "cipher": "aes-256-cbc",
    "version": 1,
    "encrypted_data": "qUhkutU4KRqlx1/7bkHtTp1hSWRJpGi76uONninr1gPmKUGCk39ZZocaWwVD\n+swP\n"
  },
  "Finetunes": {
    "iv": "ooj30oESHVkm66rYaoUfEA==\n",
    "cipher": "aes-256-cbc",
    "version": 1,
    "encrypted_data": "9t15mXxB+B5I1wn0mxymncEUUyGW7bVWu5OdrLcKuit7qSmN9/H+uiSEtQ4Y\n53bh\n"
  },
  "DigDis": {
    "iv": "2cr0hmHSHX++y41l2Z1rTw==\n",
    "cipher": "aes-256-cbc",
    "version": 1,
    "encrypted_data": "mzk4+sMdRFXUV6WDLvf9zy5aryFfmVm/i6FpCx13n2ey/lTAnnPHm7ZsDk8z\nJCKf\n"
  },
  "House_Planet": {
    "iv": "X8bMk+/a58TjYbId/IwXTg==\n",
    "cipher": "aes-256-cbc",
    "version": 1,
    "encrypted_data": "WZvE44ZArVKtVoAuiCR72wxuR2q9kq07ow5mJrM2vGZ5pxoYXmkXaCJW8Ss7\nUSa9\n"
  },
  "contentenc": {
    "iv": "kFAzdQin3hiYzivNflmdLQ==\n",
    "cipher": "aes-256-cbc",
    "version": 1,
    "encrypted_data": "oKoxVpgOcR6JLYG0e/i79aXFYiN5Aed4teRFZ9QfsgBLHRBGoRxYljLIU2gt\nOofl\n"
  },
  "WTFMarcMaron": {
    "iv": "r9mETYJ/YasugFfJbjVuUQ==\n",
    "cipher": "aes-256-cbc",
    "version": 1,
    "encrypted_data": "sKXgxWDObgLErLXEpp7Uu1iy0LC8nEX980JOAkKMUFgcOF3adnrv2xWZS2Iu\n8RsO\n"
  },
  "wor": {
    "iv": "CVaeeeHkLBF2YPrC6DMvaQ==\n",
    "cipher": "aes-256-cbc",
    "version": 1,
    "encrypted_data": "G/Hgw8TqVGzkpEJwvcLVZaiF+9kiE6DVKZ1tX6FP+DOQJxD9W9mCLrTRAS4l\nT9+x7DVv2ujjhgvHcdtI449ciA==\n"
  },
  "theonion": {
    "iv": "00J11sH0W8vlRSzCoUuUTQ==\n",
    "cipher": "aes-256-cbc",
    "version": 1,
    "encrypted_data": "4klHfSfLFZN0vm7TAindZjd7ETSESF7et1pQb+2vJLOijIgA/XnLuhBj2C1j\nK6Mh\n"
  },
  "Symphonic": {
    "iv": "ixUAAMYhjFIbfYWJ042TgA==\n",
    "cipher": "aes-256-cbc",
    "version": 1,
    "encrypted_data": "gy7lCnjFS56FaUA8/2aIfhV7eVj6mbt8J/SBy56X8O5zgBMr12y1xQ7RYGAB\n5OZE\n"
  },
  "sundesire": {
    "iv": "NL3AluHteHR4YoPgdPyhLw==\n",
    "cipher": "aes-256-cbc",
    "version": 1,
    "encrypted_data": "0crAhnWz1JJi4p5lxl/KHAfffKYZJWXFAMF1xakG2WuC4miBVwLYL5pJeAK6\nZd5r\n"
  },
  "catapult": {
    "iv": "HII1llRchoQcINdiRPeaNQ==\n",
    "cipher": "aes-256-cbc",
    "version": 1,
    "encrypted_data": "tMSo242nbtEQqi/rnA38NOSU/xelma1roxJA3jmYoBc6Oeplq0IAsdAZeHMf\nZeCW\n"
  },
  "independent": {
    "iv": "SDIp9oR4JTt/5IkhS2oHrw==\n",
    "cipher": "aes-256-cbc",
    "version": 1,
    "encrypted_data": "S+xU9d+V769CY/KRdylp2wM/k8km9clfeSfQVkjbYlpdq9R3WvekiV9+1YO1\ncjwl\n"
  },
  "jillianmichaels": {
    "iv": "8XoDrXdLXBWQIlYGb3aZPA==\n",
    "cipher": "aes-256-cbc",
    "version": 1,
    "encrypted_data": "53wRVSPXRCw1baO6qYpZzHg/LfARV5H7cpN1k2/LpKNIgTlININV7poNcZmA\nF4AH\n"
  },
  "fsr": {
    "iv": "U/srK0fGCqLhxcxFD6dN2Q==\n",
    "cipher": "aes-256-cbc",
    "version": 1,
    "encrypted_data": "G39tcRzujlyDFy5n4oc+uR5Ql/Oyo4Co5yjVYJAspdMHBuus/FxPu35tegBG\nmEl2\n"
  },
  "Tunecore": {
    "iv": "akq37YCxUdGppFGjwwwEYg==\n",
    "cipher": "aes-256-cbc",
    "version": 1,
    "encrypted_data": "bEm5z0aCrmwig9aLajK+6nzWPKhl5dOQlk+yUOIkD2E3tNsapxqt/o+77LGL\nk5TM\n"
  },
  "consolidated": {
    "iv": "WAbYtARioOPBSQTBnwVxDQ==\n",
    "cipher": "aes-256-cbc",
    "version": 1,
    "encrypted_data": "2kBeif3C5MoRtgDgnFt2wQkkdqVqbRYYZppUh4VWiNKp7X6ZZ1Gq7gir37U6\nG3C3\n"
  },
  "nextplateau": {
    "iv": "OyALz8cgYbdrTOY0bYVmBQ==\n",
    "cipher": "aes-256-cbc",
    "version": 1,
    "encrypted_data": "TbrkJuqI2o4KupTLkKxyV45UifVwV0hwTSCbhZ3eMxUIgDUhluebqz2KEmCj\n829M\n"
  },
  "id": "upload_users",
  "blaze": {
    "iv": "0mP8MBmshL90zRELJl6Nwg==\n",
    "cipher": "aes-256-cbc",
    "version": 1,
    "encrypted_data": "lEXnd9krk2RwV8uF4B5hJ3XP03VLJ9KOjAzbIkF4QxsmSxwgndg8w8z/WHmJ\nqQr7\n"
  },
  "Envision": {
    "iv": "V1QyGeYmd541vTKwMhsQyQ==\n",
    "cipher": "aes-256-cbc",
    "version": 1,
    "encrypted_data": "K+qcFNOZ2Jqw2YLCHoPZUwqpwIU/cLwkI472b7ePPaZFvOw0bsKsFRkcj1Oz\n+TIM\n"
  },
  "wmg": {
    "iv": "3hat6MZCqHGNsIQpBpg/Yw==\n",
    "cipher": "aes-256-cbc",
    "version": 1,
    "encrypted_data": "vhd7zm3pS27x6sUn08q6rCJ5+h3aAp7Y7ngWPsP0oupCjzLGISFnzKioYrte\nQdNC\n"
  },
  "unapologetic": {
    "iv": "HHtXaWflBmFRQIpuROQgng==\n",
    "cipher": "aes-256-cbc",
    "version": 1,
    "encrypted_data": "x2zdu4ArrWwBlCUuS0QXf/GtHEYbk6YTQUKvHMDIm/rRdALhvLH8/ZBNBSwq\nX5MC\n"
  },
  "conan": {
    "iv": "cq8Y/GmN7A2ebd5mIxlUrg==\n",
    "cipher": "aes-256-cbc",
    "version": 1,
    "encrypted_data": "KxYBXE/4imbF9UHX/DkDcc2eEpKVoo/SB5Q+wAdXXRITbXeeCeiFKxljq9g6\nhsf1\n"
  },
  "Bloomberg": {
    "iv": "Zi46o+fMHHpRL+lgamP5lg==\n",
    "cipher": "aes-256-cbc",
    "version": 1,
    "encrypted_data": "mWI/ntDi+Y59bUs/yflKxoFuOutg5HaH3Hazc6vjxXtIsRUaIOi0xZyjOJQx\nQML2\n"
  },
  "Compass": {
    "iv": "7BgIawq8l8RPpZWIEcTBzQ==\n",
    "cipher": "aes-256-cbc",
    "version": 1,
    "encrypted_data": "gyTMzWXoW0tMQ+lDWKeh7F9/3PWVBeBsSEBZPgnmkHKnpnmNunnBqkhXaZ/Y\nqiBL\n"
  },
  "fromscratch": {
    "iv": "3sVQ1vv1iwT1At8UvIGkjw==\n",
    "cipher": "aes-256-cbc",
    "version": 1,
    "encrypted_data": "6ZT5bL5WoGbBfrSNRypIunrVPHvi3m/ZsllNe/xIrvZBfnmOXU4BzgLMO6MX\n0wDz\n"
  },
  "bob_tom": {
    "iv": "ZE0t5Yt71RM6zOSg8fRQTA==\n",
    "cipher": "aes-256-cbc",
    "version": 1,
    "encrypted_data": "nr7BXzEnbE1aMzO/OcO8TpZMlQnAONOTKOlSSyV/a/zvT4g8ia3LoDcjAhc/\nbU/K\n"
  },
  "alienprod": {
    "iv": "y3ZpPlJpl7HW0j5gNWTlMQ==\n",
    "cipher": "aes-256-cbc",
    "version": 1,
    "encrypted_data": "iWkGwqTM5yLEo+Tc9bVyk8sMqQH0RfX3Tk7qCcqjeT1OkjrGzASAId5YW9KY\nU3rd\n"
  },
  "jeff_corwin": {
    "iv": "KIFlrXqlHHw57PuGpJTRVg==\n",
    "cipher": "aes-256-cbc",
    "version": 1,
    "encrypted_data": "aOuVElZUIL02XMDlJWPFU/mUWGMY8itIiUBypKR5YBCvJljgDRoEAYzRfiuk\nNpDD\n"
  },
  "CombatJack": {
    "iv": "09VLHTqEQGDgR6r0CUy6Jg==\n",
    "cipher": "aes-256-cbc",
    "version": 1,
    "encrypted_data": "+AUzZff3+qJG7s4mlr2TljTTWdJeE0fjDGD2KDMuWwo2M3xaDSmobJ8mdXR8\nMjos\n"
  },
  "cio": {
    "iv": "eDJ0/VgBtNpl4N01T2u6fw==\n",
    "cipher": "aes-256-cbc",
    "version": 1,
    "encrypted_data": "bWk4nQa2esTp0fxIOFKDCXlpkLEZxe0wwLb9YCTi4cEWCaG3L0V1IB1VEU8w\nuvM/hrg7mv50tozQOGyZNXV4kw==\n"
  },
  "naxos": {
    "iv": "iqxXEyAh2/T0a60JuUzv3A==\n",
    "cipher": "aes-256-cbc",
    "version": 1,
    "encrypted_data": "MDFfwolox/Fi0Xm+DIHOBbaO8L3KqSP5bdan6FTh0iDUtgBBZAw8DoG411KN\no/Xq\n"
  },
  "spreaker": {
    "iv": "mlB8i7Epm2vzjVFz7GBD2w==\n",
    "cipher": "aes-256-cbc",
    "version": 1,
    "encrypted_data": "qe0cwRuNyKNDSsMjwtrp0QAohuXJqtzRMZ9iRAp99BtxgJt3n7ZQAYP1Om2+\n0++a\n"
  },
  "Steve_Harvey": {
    "iv": "j+UXMkLZTA4qrXyxEScIXw==\n",
    "cipher": "aes-256-cbc",
    "version": 1,
    "encrypted_data": "oM2FWCRJZBmmjrZJa6oBWAS5GhqBjU3aOVcoA5GmR3omz2OCQevf///OcWHP\n0hp4\n"
  },
  "LearnVest": {
    "iv": "iD4hjSqiYMNXj1CiP0q0Fg==\n",
    "cipher": "aes-256-cbc",
    "version": 1,
    "encrypted_data": "GNSETtZqJ5xOI2E2V+cl/dPQ3Me/FU9oUoazy/k9TN+KZgPTxWpTMKN1SLoR\nCrH1\n"
  },
  "IRIS": {
    "iv": "DDYgMqaTCLoNsdhJEKrUyw==\n",
    "cipher": "aes-256-cbc",
    "version": 1,
    "encrypted_data": "eNp3MFmKZkzqsCAqeJJXH4SyMJgxfrBIP2ELRQW+H40rNZU8nEtmM02RnwAX\nd/SG\n"
  },
  "Enision": {
    "iv": "jYmpqFqAzq5Y/kUtoYQoZw==\n",
    "cipher": "aes-256-cbc",
    "version": 1,
    "encrypted_data": "hpdZmWbHUC2+FgCDaMEWU480z0pY4Q+jxdMmrbAzki8d2thIKXrK5EoSkmm3\n/O3m\n"
  },
  "gail_mcwilliams": {
    "iv": "tpGZlIa6G75DlvFqs3lShg==\n",
    "cipher": "aes-256-cbc",
    "version": 1,
    "encrypted_data": "Wzkp1LJoBho64G4tOk8saG44hOKySq+NBqsFV0p+T2COxb5S+cwMEoNt/eKB\nWfzx\n"
  },
  "dashgo": {
    "iv": "rbBygFA7JqgkPBdmKuVEww==\n",
    "cipher": "aes-256-cbc",
    "version": 1,
    "encrypted_data": "qbv3VqlxnYndZJY24hykVSno5wkcY2aXKY+cwrr4YLy1XXWwLdlNDmgXGbcA\nUZy1\n"
  }
}
